{
    "config.hook.user": {
        "class": "SoosyzeCore\\Config\\Services\\HookUser",
        "arguments": [
            "@core"
        ],
        "hooks": {
            "user.permission.module": "hookPermission",
            "route.config.index" : "hookConfigIndex",
            "route.config.edit": "hookConfigManage",
            "route.config.update": "hookConfigManage"
        }
    },
    "config.install": {
        "class": "SoosyzeCore\\Config\\Installer",
        "hooks": {
            "install.user": "hookInstallUser",
            "install.menu": "hookInstallMenu"
        }
    }
}